README
setup.py
autoforms/__init__.py
autoforms/admin.py
autoforms/forms.py
autoforms/models.py
autoforms/signal.py
autoforms/tests.py
autoforms/urls.py
autoforms/views.py
autoforms.egg-info/PKG-INFO
autoforms.egg-info/SOURCES.txt
autoforms.egg-info/dependency_links.txt
autoforms.egg-info/top_level.txt
autoforms/locale/__init__.py
autoforms/templatetags/__init__.py
autoforms/templatetags/autoforms.py
sample/__init__.py
sample/manage.py
sample/settings.py
sample/urls.py