Metadata-Version: 1.0
Name: autoforms
Version: 0.5
Summary: Custom form engine for django
Home-page: http://autoforms.sandbox.jeffkit.info
Author: jeff kit
Author-email: bbmyth@gmail.com
License: UNKNOWN
Platform: UNKNOWN
